LICENSE
README.md
setup.py
bin/rdpy3-rdpclient.py
bin/rdpy3-rdphoneypot.py
bin/rdpy3-rdpmitm.py
bin/rdpy3-rdpscreenshot.py
bin/rdpy3-rssplayer.py
bin/rdpy3-vncclient.py
bin/rdpy3-vncscreenshot.py
ext/rle.c
rdpy3/__init__.py
rdpy3.egg-info/PKG-INFO
rdpy3.egg-info/SOURCES.txt
rdpy3.egg-info/dependency_links.txt
rdpy3.egg-info/requires.txt
rdpy3.egg-info/top_level.txt
rdpy3/core/nla/__init__.py
rdpy3/core/nla/cssp.py
rdpy3/core/nla/ntlm.py
rdpy3/core/nla/sspi.py
rdpy3/core/pdu/__init__.py
rdpy3/core/pdu/caps.py
rdpy3/core/pdu/data.py
rdpy3/core/pdu/layer.py
rdpy3/core/pdu/order.py
rdpy3/core/t125/__init__.py
rdpy3/core/t125/ber.py
rdpy3/core/t125/gcc.py
rdpy3/core/t125/mcs.py
rdpy3/core/t125/per.py
rdpy3/model/__init__.py
rdpy3/model/const.py
rdpy3/model/error.py
rdpy3/model/filetimes.py
rdpy3/model/layer.py
rdpy3/model/log.py
rdpy3/model/message.py
rdpy3/model/rss.py
rdpy3/model/scancode.py
rdpy3/security/__init__.py
rdpy3/security/pyDes.py
rdpy3/security/rc4.py
rdpy3/security/rsa_wrapper.py
rdpy3/security/x509.py
rdpy3/ui/__init__.py
rdpy3/ui/qt5.py
rdpy3/ui/view.py
test/test_core_const.py
test/test_core_layer.py
test/test_core_type.py
test/test_protocol_rdp_ber.py
test/test_protocol_rdp_cssp_ntlm.py
test/test_protocol_rdp_lic.py
test/test_protocol_rdp_mcs.py
test/test_protocol_rdp_per.py
test/test_protocol_rdp_rc4.py
test/test_protocol_rdp_tpkt.py
test/test_protocol_rdp_x224.py
test/test_protocol_rfb_rfb.py