Metadata-Version: 2.1
Name: rdpy3
Version: 2.0.2
Summary: Remote Desktop Protocol in Python3
Home-page: https://github.com/james4ever0/rdpy3
Author: Sylvain Peyrefitte
Author-email: citronneur@gmail.com
Requires-Python: >=3
License-File: LICENSE
